{
	"configurations" : 
	[
		{
			"directories" : 
			[
				{
					"build" : ".",
					"hasInstallRule" : true,
					"minimumCMakeVersion" : 
					{
						"string" : "3.0"
					},
					"projectIndex" : 0,
					"source" : ".",
					"targetIndexes" : 
					[
						0
					]
				}
			],
			"name" : "Release",
			"projects" : 
			[
				{
					"directoryIndexes" : 
					[
						0
					],
					"name" : "testpipe1",
					"targetIndexes" : 
					[
						0
					]
				}
			],
			"targets" : 
			[
				{
					"directoryIndex" : 0,
					"id" : "testpipe1::@6890427a1f51a3e7e1df",
					"jsonFile" : "target-testpipe1-Release-b97672271ba6611956ea.json",
					"name" : "testpipe1",
					"projectIndex" : 0
				}
			]
		}
	],
	"kind" : "codemodel",
	"paths" : 
	{
		"build" : "/usr/home/ayeka/Programming/C/GURPS/TestPIPE1/build",
		"source" : "/usr/home/ayeka/Programming/C/GURPS/TestPIPE1"
	},
	"version" : 
	{
		"major" : 2,
		"minor" : 2
	}
}
